preposterous/__init__.py
preposterous/preposterous.py
preposterous-0.0.2.dist-info/METADATA
preposterous-0.0.2.dist-info/RECORD
preposterous-0.0.2.dist-info/WHEEL
preposterous-0.0.2.dist-info/top_level.txt
