Metadata-Version: 2.1
Name: preposterous
Version: 0.0.2
Summary: A simple library for estimating the impact of an intervention, with humility
Home-page: https://github.com/matthewwritter/preposterous
Author: Matthew Ritter
Maintainer: Matthew Ritter
License: MIT
Keywords: quantified self,quantifiedself,statistics,bayesian statistics,time series
Platform: UNKNOWN
Classifier: Programming Language :: Python
Classifier: Topic :: Software Development :: Libraries :: Python Modules
Classifier: Natural Language :: English
Classifier: Intended Audience :: Science/Research
Classifier: Operating System :: OS Independent
Provides-Extra: testing
Requires-Dist: ipython (==6.5.0)
Requires-Dist: numpy (==1.15.0)
Requires-Dist: pandas (==0.23.3)
Requires-Dist: pytest (==3.7.1)
Requires-Dist: scipy (==1.1.0)
Requires-Dist: pypandoc (==1.4.0)
Requires-Dist: matplotlib (>=2.2.2)
Provides-Extra: testing
Requires-Dist: pytest; extra == 'testing'
